replay_monitor/__init__.py
replay_monitor/db.py
replay_monitor/monitor.py
replay_monitor/server.py
replay_monitor-0.0.5.dist-info/LICENSE
replay_monitor-0.0.5.dist-info/METADATA
replay_monitor-0.0.5.dist-info/WHEEL
replay_monitor-0.0.5.dist-info/entry_points.txt
replay_monitor-0.0.5.dist-info/top_level.txt
replay_monitor-0.0.5.dist-info/RECORD
