Metadata-Version: 2.1
Name: replay-monitor
Version: 0.0.5
Summary: A tool for easy data exploration in reinforcement learning environments.
Home-page: https://github.com/liorcohen5/replay-monitor
Author: Leor Cohen
Author-email: liorcohen5@gmail.com
License: UNKNOWN
Download-URL: https://github.com/liorcohen5/replay-monitor/archive/0.0.5.tar.gz
Keywords: reinforcement learning,tool,data exploration,replay,monitor,analytical tool
Platform: UNKNOWN
Classifier: Programming Language :: Python :: 3
Classifier: License :: OSI Approved :: MIT License
Classifier: Operating System :: OS Independent
Requires-Python: >=3.6
Requires-Dist: gym
Requires-Dist: bokeh
Requires-Dist: tensorflow
Requires-Dist: numpy
Requires-Dist: tables
